blkmrln/__init__.py
blkmrln/__main__.py
blkmrln/cli.py
blkmrln/core.py
blkmrln/utils.py
blkmrln/commands/__init__.py
blkmrln/commands/build.py
blkmrln/commands/debug.py
blkmrln/commands/diagram.py
blkmrln/commands/feature.py
blkmrln/commands/format.py
blkmrln/commands/project.py
blkmrln/commands/run.py
blkmrln/commands/test.py
blkmrln/commands/venvmanager.py
blkmrln/resources/__init__.py
blkmrln/resources/setup.py
blkmrln/resources/build/tmp.txt
blkmrln/resources/common/__init__.py
blkmrln/resources/common/app/__init__.py
blkmrln/resources/common/app/config_manager_base.py
blkmrln/resources/common/test/__init__.py
blkmrln/resources/config/example/env_config.yaml
blkmrln/resources/config/example/secrets/config.yaml
blkmrln/resources/dep/common/requirements.txt
blkmrln/resources/src/example/__main__.py
blkmrln/resources/src/example/config_manager.py
common/__init__.py
common/app/__init__.py
common/app/config_manager_base.py
common/test/__init__.py
blkmrln-0.1.0.dist-info/LICENSE
blkmrln-0.1.0.dist-info/METADATA
blkmrln-0.1.0.dist-info/WHEEL
blkmrln-0.1.0.dist-info/entry_points.txt
blkmrln-0.1.0.dist-info/top_level.txt
blkmrln-0.1.0.dist-info/RECORD
